LICENSE
README.md
setup.cfg
setup.py
db2xlsx/__init__.py
db2xlsx/converter.py
db2xlsx.egg-info/PKG-INFO
db2xlsx.egg-info/SOURCES.txt
db2xlsx.egg-info/dependency_links.txt
db2xlsx.egg-info/top_level.txt