Metadata-Version: 2.1
Name: db2xlsx
Version: 0.2
Summary: Convert your *.db files to *.xlsx
Home-page: UNKNOWN
Author: saikonohack
Author-email: saintklovus@gmail.com
License: UNKNOWN
Platform: UNKNOWN
Classifier: Programming Language :: Python :: 3.8
Classifier: License :: OSI Approved :: MIT License
Classifier: Operating System :: OS Independent
Requires-Python: >=3.6
License-File: LICENSE
